top/__init__.py
top/api/__init__.py
top/api/base.py
top/api/rest/TbkCouponGetRequest.py
top/api/rest/TbkItemInfoGetRequest.py
top/api/rest/TbkTpwdCreateRequest.py
top/api/rest/__init__.py
taobao_sdk_python3-1.0.2.dist-info/LICENSE
taobao_sdk_python3-1.0.2.dist-info/METADATA
taobao_sdk_python3-1.0.2.dist-info/WHEEL
taobao_sdk_python3-1.0.2.dist-info/top_level.txt
taobao_sdk_python3-1.0.2.dist-info/RECORD
