Metadata-Version: 2.1
Name: taobao-sdk-python3
Version: 1.0.2
Summary: taobao_sdk_python3
Home-page: https://github.com/ymj4023/taobao_sdk_python3
Author: ymj4023
Author-email: xuerobec@foxmail.com
License: MIT
Platform: UNKNOWN
Classifier: Topic :: Software Development :: Libraries :: Python Modules
Classifier: Programming Language :: Python
Classifier: Programming Language :: Python :: 3.4
Classifier: Programming Language :: Python :: 3.5
Classifier: Programming Language :: Python :: 3.5
Classifier: Programming Language :: Python :: 3.6
Classifier: Programming Language :: Python :: 3.7
Classifier: Programming Language :: Python :: 3.8
Classifier: Programming Language :: Python :: 3.9
Requires-Python: ~=3.4
